osprojects/__init__.py
osprojects/check_project.py
osprojects/checkos.py
osprojects/editor.py
osprojects/github_api.py
osprojects/osproject.py
pyopensourceprojects-0.5.0.dist-info/METADATA
pyopensourceprojects-0.5.0.dist-info/WHEEL
pyopensourceprojects-0.5.0.dist-info/entry_points.txt
pyopensourceprojects-0.5.0.dist-info/licenses/LICENSE
pyopensourceprojects-0.5.0.dist-info/RECORD
