Metadata-Version: 2.4
Name: pyOpenSourceProjects
Version: 0.5.0
Summary: Check python OpenSource Projects to follow standards for README, github workflow and pyprojec.toml - creates badges
Project-URL: Home, https://github.com/WolfgangFahl/pyOpenSourceProjects
Project-URL: Documentation, http://wiki.bitplan.com/index.php/pyOpenSourceProjects
Project-URL: Source, https://github.com/WolfgangFahl/pyOpenSourceProjects
Author-email: Wolfgang Fahl <wf@bitplan.com>
Maintainer-email: Wolfgang Fahl <wf@bitplan.com>
License-Expression: Apache-2.0
License-File: LICENSE
Classifier: Programming Language :: Python
Classifier: Programming Language :: Python :: 3.10
Classifier: Programming Language :: Python :: 3.11
Classifier: Programming Language :: Python :: 3.12
Classifier: Programming Language :: Python :: 3.13
Requires-Python: >=3.10
Requires-Dist: backoff
Requires-Dist: beautifulsoup4>=4.14.2
Requires-Dist: gitpython
Requires-Dist: packaging>=24.1
Requires-Dist: py-3rdparty-mediawiki>=0.18.1
Requires-Dist: pylodstorage>=0.17.0
Requires-Dist: python-dateutil>=2.8.2
Requires-Dist: ratelimit>=2.2.1
Requires-Dist: requests
Requires-Dist: tomli>=2.3.0; python_version < '3.11'
Requires-Dist: tqdm>=4.66.5
Provides-Extra: test
